block.v
module block(in, rule, out);
    input wire[2:0] in;
    input wire[7:0] rule;

    output wire out;

    assign out = rule[in];
endmodule

Automaton-Verilog-Nbits/automaton.v
module automaton #(parameter WIDTH = 8) 
  ( input wire clk,           //-- IN: Reloj de la FPGA
    output wire [WIDTH-1:0] data    //-- OUT: Salida del Cellular Automaton --> a los leds
  );

  //-- Bits para el prescaler
  parameter N = 23;
  parameter SEED = 8'b00000001; // 1a linea (semilla) del Cellular Automaton
  parameter RULE = 129;
  
  wire [7:0] rule = RULE;

  //-- Reloj principal (prescalado)
  wire clk_base;

  //-- Instanciar el prescaler
  prescaler #(.N(N)) PRES ( .clk_in(clk), .clk_out(clk_base) );

  //-- Instanciar el Inicializador
  wire sel;
  init INIT ( clk_base, sel );

  // ver Diseño del T13  --> inicializador --> selector (mux2-1)

  //-- Cable salida del cellAutomaton (CA) al registro R
  wire [WIDTH-1:0] rin;

  // mux2-1 (saca SEED si sel=0, sino la salida del registro (detras del Cellular Automaton))
  assign data = (sel == 0) ? SEED : rout;

  cellAutomaton #(.WIDTH(WIDTH)) CA ( .in(data), .rule(rule), .out(rin));

  //-- Registro R de WIDTH bits
  reg [WIDTH-1:0] rout;
  always @(posedge(clk_base))
    rout <= rin; // Pasamos la salida del Cellular Automaton a la salida del registro en cada positive edge

endmodule

module cellAutomaton #(parameter WIDTH = 8) 
  ( input wire [WIDTH-1:0] in,
    input wire [7:0] rule,
    output wire [WIDTH-1:0] out
  );

  //-- Apply the Cellular Automaton rule (compute "next line")
  // block B0( { in[7], in[0], in[1] }, rule, out[0] );
  // block B1( { in[0], in[1], in[2] }, rule, out[1] );
  // block B2( { in[1], in[2], in[3] }, rule, out[2] );
  // block B3( { in[2], in[3], in[4] }, rule, out[3] );
  // block B4( { in[3], in[4], in[5] }, rule, out[4] );
  // block B5( { in[4], in[5], in[6] }, rule, out[5] );
  // block B6( { in[5], in[6], in[7] }, rule, out[6] );
  // block B7( { in[6], in[7], in[0] }, rule, out[7] );

  genvar i;
  generate
    for (i=0; i<WIDTH; i=i+1)
    begin : automaton_cell
      block Bi( { in[ (i==0) ? WIDTH-1 : (i-1) ], in[i], in[ ( i == (WIDTH-1) ) ? 0 : i+1 ] }, rule, out[i] );
      // case (i)
      //   0:  
      //     block B0( { in[WIDTH-1], in[0], in[1] }, rule, out[0] );
      //   WIDTH-1:
      //     block BW( { in[WIDTH-2], in[WIDTH-1], in[0] }, rule, out[WIDTH-1] );
      //   default: 
      //     block Bi( { in[i-1], in[i], in[i+1] }, rule, out[i] );
      // endcase
    end 
  endgenerate

endmodule

Automaton-Verilog-Nbits/init.v
//-- init.v  (version optimizada)
module init(input wire clk, output ini);
    //-- Registro de 1 bit inicializa a 0 (solo para simulacion)
    //-- Al sintetizarlo siempre estará a cero con independencia 
    //-- del valor al que lo pongamos
    reg ini = 0;

    //-- En flanco de subida sacamos un "1" por la salida
    always @(posedge(clk))
        ini <= 1;

endmodule

Automaton-VGA-80bit/prescaler.v
//-------------------------------------------------------------
//-- Prescaler de N bits
//-- (C) BQ. August 2015. Written by Juan Gonzalez (obijuan)
//-------------------------------------------------------------
//-- Prescaler generico, para ralentizar las señales de reloj
//-------------------------------------------------------------

//-- Entrada: señal de reloj de entrada
//-- Salida: Señal de reloj de salida, con menor frecuencia

`default_nettype none

module prescaler(input clk_in, output clk_out);
  wire clk_in;
  wire clk_out;

  //-- Numero de bits del prescaler (por defecto)
  parameter N = 22;

  //-- Registro para implementar contador de N bits
  reg [N-1:0] count = 0;

  //-- El bit más significativo se saca por la salida
  assign clk_out = count[N-1];

  //-- Contador: se incrementa en flanco de subida
  always @(posedge(clk_in)) begin
    count <= count + 1;
  end

endmodule

automaton_tb.v
module automaton_tb();

	parameter WIDTH = 128;

    reg[7:0] count = 0;

	//-- Registro para generar la señal de reloj
	reg clk = 0;

	//-- Datos de salida del componente
	wire [WIDTH-1:0] data;

	//-- Instanciar el componente (N=1 aqui, segundos)
	automaton #(.WIDTH(WIDTH)) myCA ( .clk(clk), .data(data) );
	defparam myCA.N=1;
	defparam myCA.RULE=126; // http://mathworld.wolfram.com/Rule126.html
	defparam myCA.SEED = 2**(WIDTH/2);

	//-- Generador de reloj. Periodo 2 unidades
	always #1 clk = ~clk;

	//-- Proceso al inicio
	initial begin

		//-- Fichero donde almacenar los resultados
		$dumpfile("automaton_tb.vcd");
		$dumpvars(0, automaton_tb);

		#1 $display("data: %b", data);

        for (count=0; count<=250; count=count+1)
        begin
            #4
            $display("data: %b", data);
        end

		# 1 $display("FIN de la simulacion");
		$finish;

	end

endmodule

automaton_tb.vcd
$date
	Wed Jan 17 07:57:32 2018
$end
$version
	Icarus Verilog
$end
$timescale
	1s
$end
$scope module automaton_tb $end
$var wire 8 ! data [7:0] $end
$var reg 1 " clk $end
$var reg 8 # count [7:0] $end
$scope module myCA $end
$var wire 1 " clk $end
$var wire 8 $ rule [7:0] $end
$var wire 1 % sel $end
$var wire 8 & rin [7:0] $end
$var wire 8 ' data [7:0] $end
$var wire 1 ( clk_base $end
$var reg 8 ) rout [7:0] $end
$scope module CA $end
$var wire 8 * in [7:0] $end
$var wire 8 + rule [7:0] $end
$var wire 8 , out [7:0] $end
$scope begin automaton_cell[0] $end
$scope module Bi $end
$var wire 3 - in [2:0] $end
$var wire 8 . rule [7:0] $end
$var wire 1 / out $end
$upscope $end
$upscope $end
$scope begin automaton_cell[1] $end
$scope module Bi $end
$var wire 3 0 in [2:0] $end
$var wire 8 1 rule [7:0] $end
$var wire 1 2 out $end
$upscope $end
$upscope $end
$scope begin automaton_cell[2] $end
$scope module Bi $end
$var wire 3 3 in [2:0] $end
$var wire 8 4 rule [7:0] $end
$var wire 1 5 out $end
$upscope $end
$upscope $end
$scope begin automaton_cell[3] $end
$scope module Bi $end
$var wire 3 6 in [2:0] $end
$var wire 8 7 rule [7:0] $end
$var wire 1 8 out $end
$upscope $end
$upscope $end
$scope begin automaton_cell[4] $end
$scope module Bi $end
$var wire 3 9 in [2:0] $end
$var wire 8 : rule [7:0] $end
$var wire 1 ; out $end
$upscope $end
$upscope $end
$scope begin automaton_cell[5] $end
$scope module Bi $end
$var wire 3 < in [2:0] $end
$var wire 8 = rule [7:0] $end
$var wire 1 > out $end
$upscope $end
$upscope $end
$scope begin automaton_cell[6] $end
$scope module Bi $end
$var wire 3 ? in [2:0] $end
$var wire 8 @ rule [7:0] $end
$var wire 1 A out $end
$upscope $end
$upscope $end
$scope begin automaton_cell[7] $end
$scope module Bi $end
$var wire 3 B in [2:0] $end
$var wire 8 C rule [7:0] $end
$var wire 1 D out $end
$upscope $end
$upscope $end
$upscope $end
$scope module INIT $end
$var wire 1 ( clk $end
$var reg 1 % ini $end
$upscope $end
$scope module PRES $end
$var wire 1 " clk_in $end
$var wire 1 ( clk_out $end
$var reg 1 E count $end
$upscope $end
$upscope $end
$upscope $end
$enddefinitions $end
#0
$dumpvars
0E
0D
b1111110 C
b0 B
0A
b1111110 @
b0 ?
1>
b1111110 =
b100 <
1;
b1111110 :
b10 9
18
b1111110 7
b1 6
05
b1111110 4
b0 3
02
b1111110 1
b0 0
0/
b1111110 .
b0 -
b111000 ,
b1111110 +
b10000 *
bx )
0(
b10000 '
b111000 &
0%
b1111110 $
b0 #
0"
b10000 !
$end
#1
15
b1 3
b11 6
0;
b111 9
b110 <
b1101100 &
b1101100 ,
1A
b100 ?
b111000 !
b111000 '
b111000 *
1%
b111000 )
1(
1E
1"
#2
0"
#3
0(
0E
1"
#4
0"
#5
12
b1 0
b11 3
b110 6
1;
b101 9
1>
b11 <
b110 ?
b11111110 &
b11111110 ,
1D
b100 B
b1101100 !
b1101100 '
b1101100 *
b1101100 )
1(
1E
1"
b1 #
#6
0"
#7
0(
0E
1"
#8
0"
#9
1/
b101 -
b11 0
05
b111 3
08
b111 6
0;
b111 9
0>
b111 <
b10000011 &
b10000011 ,
0A
b111 ?
b110 B
b11111110 !
b11111110 '
b11111110 *
b11111110 )
1(
1E
1"
b10 #
#10
0"
#11
0(
0E
1"
#12
0"
#13
0/
b111 -
b110 0
15
b100 3
08
b0 6
0;
b0 9
0>
b0 <
1A
b1 ?
b11000110 &
b11000110 ,
1D
b11 B
b10000011 !
b10000011 '
b10000011 *
b10000011 )
1(
1E
1"
b11 #
#14
0"
#15
0(
0E
1"
#16
0"
#17
1/
b101 -
12
b11 0
b110 3
18
b100 6
b11101111 &
b11101111 ,
1>
b1 <
b11 ?
b110 B
b11000110 !
b11000110 '
b11000110 *
b11000110 )
1(
1E
1"
b100 #
#18
0"
#19
0(
0E
1"
#20
0"
#21
0/
b111 -
02
b111 0
05
b111 3
b110 6
1;
b101 9
b11 <
0A
b111 ?
b111000 &
b111000 ,
0D
b111 B
b11101111 !
b11101111 '
b11101111 *
b11101111 )
1(
1E
1"
b101 #
#22
0"
#23
0(
0E
1"
#24
0"
#25
0/
b0 -
02
b0 0
15
b1 3
18
b11 6
0;
b111 9
b110 <
1A
b100 ?
b1101100 &
b1101100 ,
0D
b0 B
b111000 !
b111000 '
b111000 *
b111000 )
1(
1E
1"
b110 #
#26
0"
#27
0(
0E
1"
#28
0"
#29
12
b1 0
b11 3
b110 6
1;
b101 9
1>
b11 <
b110 ?
b11111110 &
b11111110 ,
1D
b100 B
b1101100 !
b1101100 '
b1101100 *
b1101100 )
1(
1E
1"
b111 #
#30
0"
#31
0(
0E
1"
#32
0"
#33
1/
b101 -
b11 0
05
b111 3
08
b111 6
0;
b111 9
0>
b111 <
b10000011 &
b10000011 ,
0A
b111 ?
b110 B
b11111110 !
b11111110 '
b11111110 *
b11111110 )
1(
1E
1"
b1000 #
#34
0"
#35
0(
0E
1"
#36
0"
#37
0/
b111 -
b110 0
15
b100 3
08
b0 6
0;
b0 9
0>
b0 <
1A
b1 ?
b11000110 &
b11000110 ,
1D
b11 B
b10000011 !
b10000011 '
b10000011 *
b10000011 )
1(
1E
1"
b1001 #
#38
0"
#39
0(
0E
1"
#40
0"
#41
1/
b101 -
12
b11 0
b110 3
18
b100 6
b11101111 &
b11101111 ,
1>
b1 <
b11 ?
b110 B
b11000110 !
b11000110 '
b11000110 *
b11000110 )
1(
1E
1"
b1010 #
#42
0"
#43
0(
0E
1"
#44
0"
#45
0/
b111 -
02
b111 0
05
b111 3
b110 6
1;
b101 9
b11 <
0A
b111 ?
b111000 &
b111000 ,
0D
b111 B
b11101111 !
b11101111 '
b11101111 *
b11101111 )
1(
1E
1"
b1011 #
#46
0"
#47
0(
0E
1"
#48
0"
#49
0/
b0 -
02
b0 0
15
b1 3
18
b11 6
0;
b111 9
b110 <
1A
b100 ?
b1101100 &
b1101100 ,
0D
b0 B
b111000 !
b111000 '
b111000 *
b111000 )
1(
1E
1"
b1100 #
#50
0"
#51
0(
0E
1"
#52
0"
#53
12
b1 0
b11 3
b110 6
1;
b101 9
1>
b11 <
b110 ?
b11111110 &
b11111110 ,
1D
b100 B
b1101100 !
b1101100 '
b1101100 *
b1101100 )
1(
1E
1"
b1101 #
#54
0"
#55
0(
0E
1"
#56
0"
#57
1/
b101 -
b11 0
05
b111 3
08
b111 6
0;
b111 9
0>
b111 <
b10000011 &
b10000011 ,
0A
b111 ?
b110 B
b11111110 !
b11111110 '
b11111110 *
b11111110 )
1(
1E
1"
b1110 #
#58
0"
#59
0(
0E
1"
#60
0"
#61
0/
b111 -
b110 0
15
b100 3
08
b0 6
0;
b0 9
0>
b0 <
1A
b1 ?
b11000110 &
b11000110 ,
1D
b11 B
b10000011 !
b10000011 '
b10000011 *
b10000011 )
1(
1E
1"
b1111 #
#62
0"
#63
0(
0E
1"
#64
0"
#65
1/
b101 -
12
b11 0
b110 3
18
b100 6
b11101111 &
b11101111 ,
1>
b1 <
b11 ?
b110 B
b11000110 !
b11000110 '
b11000110 *
b11000110 )
1(
1E
1"
b10000 #
#66
0"
#67
0(
0E
1"
#68
0"
#69
0/
b111 -
02
b111 0
05
b111 3
b110 6
1;
b101 9
b11 <
0A
b111 ?
b111000 &
b111000 ,
0D
b111 B
b11101111 !
b11101111 '
b11101111 *
b11101111 )
1(
1E
1"
b10001 #
#70
0"
#71
0(
0E
1"
#72
0"
#73
0/
b0 -
02
b0 0
15
b1 3
18
b11 6
0;
b111 9
b110 <
1A
b100 ?
b1101100 &
b1101100 ,
0D
b0 B
b111000 !
b111000 '
b111000 *
b111000 )
1(
1E
1"
b10010 #
#74
0"
#75
0(
0E
1"
#76
0"
#77
12
b1 0
b11 3
b110 6
1;
b101 9
1>
b11 <
b110 ?
b11111110 &
b11111110 ,
1D
b100 B
b1101100 !
b1101100 '
b1101100 *
b1101100 )
1(
1E
1"
b10011 #
#78
0"
#79
0(
0E
1"
#80
0"
#81
1/
b101 -
b11 0
05
b111 3
08
b111 6
0;
b111 9
0>
b111 <
b10000011 &
b10000011 ,
0A
b111 ?
b110 B
b11111110 !
b11111110 '
b11111110 *
b11111110 )
1(
1E
1"
b10100 #
#82
0"
#83
0(
0E
1"
#84
0"
#85
0/
b111 -
b110 0
15
b100 3
08
b0 6
0;
b0 9
0>
b0 <
1A
b1 ?
b11000110 &
b11000110 ,
1D
b11 B
b10000011 !
b10000011 '
b10000011 *
b10000011 )
1(
1E
1"
b10101 #
#86
0"
#87
0(
0E
1"
#88
0"
#89
1/
b101 -
12
b11 0
b110 3
18
b100 6
b11101111 &
b11101111 ,
1>
b1 <
b11 ?
b110 B
b11000110 !
b11000110 '
b11000110 *
b11000110 )
1(
1E
1"
b10110 #
#90
0"
#91
0(
0E
1"
#92
0"
#93
0/
b111 -
02
b111 0
05
b111 3
b110 6
1;
b101 9
b11 <
0A
b111 ?
b111000 &
b111000 ,
0D
b111 B
b11101111 !
b11101111 '
b11101111 *
b11101111 )
1(
1E
1"
b10111 #
#94
0"
#95
0(
0E
1"
#96
0"
#97
0/
b0 -
02
b0 0
15
b1 3
18
b11 6
0;
b111 9
b110 <
1A
b100 ?
b1101100 &
b1101100 ,
0D
b0 B
b111000 !
b111000 '
b111000 *
b111000 )
1(
1E
1"
b11000 #
#98
0"
#99
0(
0E
1"
#100
0"
#101
12
b1 0
b11 3
b110 6
1;
b101 9
1>
b11 <
b110 ?
b11111110 &
b11111110 ,
1D
b100 B
b1101100 !
b1101100 '
b1101100 *
b1101100 )
1(
1E
1"
b11001 #
#102
0"
#103
0(
0E
1"
#104
0"
#105
1/
b101 -
b11 0
05
b111 3
08
b111 6
0;
b111 9
0>
b111 <
b10000011 &
b10000011 ,
0A
b111 ?
b110 B
b11111110 !
b11111110 '
b11111110 *
b11111110 )
1(
1E
1"
b11010 #
#106
0"
#107
0(
0E
1"
#108
0"
#109
0/
b111 -
b110 0
15
b100 3
08
b0 6
0;
b0 9
0>
b0 <
1A
b1 ?
b11000110 &
b11000110 ,
1D
b11 B
b10000011 !
b10000011 '
b10000011 *
b10000011 )
1(
1E
1"
b11011 #
#110
0"
#111
0(
0E
1"
#112
0"
#113
1/
b101 -
12
b11 0
b110 3
18
b100 6
b11101111 &
b11101111 ,
1>
b1 <
b11 ?
b110 B
b11000110 !
b11000110 '
b11000110 *
b11000110 )
1(
1E
1"
b11100 #
#114
0"
#115
0(
0E
1"
#116
0"
#117
0/
b111 -
02
b111 0
05
b111 3
b110 6
1;
b101 9
b11 <
0A
b111 ?
b111000 &
b111000 ,
0D
b111 B
b11101111 !
b11101111 '
b11101111 *
b11101111 )
1(
1E
1"
b11101 #
#118
0"
#119
0(
0E
1"
#120
0"
#121
0/
b0 -
02
b0 0
15
b1 3
18
b11 6
0;
b111 9
b110 <
1A
b100 ?
b1101100 &
b1101100 ,
0D
b0 B
b111000 !
b111000 '
b111000 *
b111000 )
1(
1E
1"
b11110 #
#122
0"
#123
0(
0E
1"
#124
0"
#125
12
b1 0
b11 3
b110 6
1;
b101 9
1>
b11 <
b110 ?
b11111110 &
b11111110 ,
1D
b100 B
b1101100 !
b1101100 '
b1101100 *
b1101100 )
1(
1E
1"
b11111 #
#126
0"
#127
0(
0E
1"
#128
0"
#129
1/
b101 -
b11 0
05
b111 3
08
b111 6
0;
b111 9
0>
b111 <
b10000011 &
b10000011 ,
0A
b111 ?
b110 B
b11111110 !
b11111110 '
b11111110 *
b11111110 )
1(
1E
1"
b100000 #
#130
0"
#131
0(
0E
1"
#132
0"
#133
0/
b111 -
b110 0
15
b100 3
08
b0 6
0;
b0 9
0>
b0 <
1A
b1 ?
b11000110 &
b11000110 ,
1D
b11 B
b10000011 !
b10000011 '
b10000011 *
b10000011 )
1(
1E
1"
b100001 #
#134
0"
#135
0(
0E
1"
#136
0"
#137
1/
b101 -
12
b11 0
b110 3
18
b100 6
b11101111 &
b11101111 ,
1>
b1 <
b11 ?
b110 B
b11000110 !
b11000110 '
b11000110 *
b11000110 )
1(
1E
1"
b100010 #
#138
0"
#139
0(
0E
1"
#140
0"
#141
0/
b111 -
02
b111 0
05
b111 3
b110 6
1;
b101 9
b11 <
0A
b111 ?
b111000 &
b111000 ,
0D
b111 B
b11101111 !
b11101111 '
b11101111 *
b11101111 )
1(
1E
1"
b100011 #
#142
0"
#143
0(
0E
1"
#144
0"
#145
0/
b0 -
02
b0 0
15
b1 3
18
b11 6
0;
b111 9
b110 <
1A
b100 ?
b1101100 &
b1101100 ,
0D
b0 B
b111000 !
b111000 '
b111000 *
b111000 )
1(
1E
1"
b100100 #
#146
0"
#147
0(
0E
1"
#148
0"
#149
12
b1 0
b11 3
b110 6
1;
b101 9
1>
b11 <
b110 ?
b11111110 &
b11111110 ,
1D
b100 B
b1101100 !
b1101100 '
b1101100 *
b1101100 )
1(
1E
1"
b100101 #
#150
0"
#151
0(
0E
1"
#152
0"
#153
1/
b101 -
b11 0
05
b111 3
08
b111 6
0;
b111 9
0>
b111 <
b10000011 &
b10000011 ,
0A
b111 ?
b110 B
b11111110 !
b11111110 '
b11111110 *
b11111110 )
1(
1E
1"
b100110 #
#154
0"
#155
0(
0E
1"
#156
0"
#157
0/
b111 -
b110 0
15
b100 3
08
b0 6
0;
b0 9
0>
b0 <
1A
b1 ?
b11000110 &
b11000110 ,
1D
b11 B
b10000011 !
b10000011 '
b10000011 *
b10000011 )
1(
1E
1"
b100111 #
#158
0"
#159
0(
0E
1"
#160
0"
#161
1/
b101 -
12
b11 0
b110 3
18
b100 6
b11101111 &
b11101111 ,
1>
b1 <
b11 ?
b110 B
b11000110 !
b11000110 '
b11000110 *
b11000110 )
1(
1E
1"
b101000 #
#162
0"
#163
0(
0E
1"
#164
0"
#165
0/
b111 -
02
b111 0
05
b111 3
b110 6
1;
b101 9
b11 <
0A
b111 ?
b111000 &
b111000 ,
0D
b111 B
b11101111 !
b11101111 '
b11101111 *
b11101111 )
1(
1E
1"
b101001 #
#166
0"
#167
0(
0E
1"
#168
0"
#169
0/
b0 -
02
b0 0
15
b1 3
18
b11 6
0;
b111 9
b110 <
1A
b100 ?
b1101100 &
b1101100 ,
0D
b0 B
b111000 !
b111000 '
b111000 *
b111000 )
1(
1E
1"
b101010 #
#170
0"
#171
0(
0E
1"
#172
0"
#173
12
b1 0
b11 3
b110 6
1;
b101 9
1>
b11 <
b110 ?
b11111110 &
b11111110 ,
1D
b100 B
b1101100 !
b1101100 '
b1101100 *
b1101100 )
1(
1E
1"
b101011 #
#174
0"
#175
0(
0E
1"
#176
0"
#177
1/
b101 -
b11 0
05
b111 3
08
b111 6
0;
b111 9
0>
b111 <
b10000011 &
b10000011 ,
0A
b111 ?
b110 B
b11111110 !
b11111110 '
b11111110 *
b11111110 )
1(
1E
1"
b101100 #
#178
0"
#179
0(
0E
1"
#180
0"
#181
0/
b111 -
b110 0
15
b100 3
08
b0 6
0;
b0 9
0>
b0 <
1A
b1 ?
b11000110 &
b11000110 ,
1D
b11 B
b10000011 !
b10000011 '
b10000011 *
b10000011 )
1(
1E
1"
b101101 #
#182
0"
#183
0(
0E
1"
#184
0"
#185
1/
b101 -
12
b11 0
b110 3
18
b100 6
b11101111 &
b11101111 ,
1>
b1 <
b11 ?
b110 B
b11000110 !
b11000110 '
b11000110 *
b11000110 )
1(
1E
1"
b101110 #
#186
0"
#187
0(
0E
1"
#188
0"
#189
0/
b111 -
02
b111 0
05
b111 3
b110 6
1;
b101 9
b11 <
0A
b111 ?
b111000 &
b111000 ,
0D
b111 B
b11101111 !
b11101111 '
b11101111 *
b11101111 )
1(
1E
1"
b101111 #
#190
0"
#191
0(
0E
1"
#192
0"
#193
0/
b0 -
02
b0 0
15
b1 3
18
b11 6
0;
b111 9
b110 <
1A
b100 ?
b1101100 &
b1101100 ,
0D
b0 B
b111000 !
b111000 '
b111000 *
b111000 )
1(
1E
1"
b110000 #
#194
0"
#195
0(
0E
1"
#196
0"
#197
12
b1 0
b11 3
b110 6
1;
b101 9
1>
b11 <
b110 ?
b11111110 &
b11111110 ,
1D
b100 B
b1101100 !
b1101100 '
b1101100 *
b1101100 )
1(
1E
1"
b110001 #
#198
0"
#199
0(
0E
1"
#200
0"
#201
1/
b101 -
b11 0
05
b111 3
08
b111 6
0;
b111 9
0>
b111 <
b10000011 &
b10000011 ,
0A
b111 ?
b110 B
b11111110 !
b11111110 '
b11111110 *
b11111110 )
1(
1E
1"
b110010 #
#202
0"
#203
0(
0E
1"
#204
0"
#205
0/
b111 -
b110 0
15
b100 3
08
b0 6
0;
b0 9
0>
b0 <
1A
b1 ?
b11000110 &
b11000110 ,
1D
b11 B
b10000011 !
b10000011 '
b10000011 *
b10000011 )
1(
1E
1"
b110011 #
#206
0"
#207
0(
0E
1"
#208
0"
#209
1/
b101 -
12
b11 0
b110 3
18
b100 6
b11101111 &
b11101111 ,
1>
b1 <
b11 ?
b110 B
b11000110 !
b11000110 '
b11000110 *
b11000110 )
1(
1E
1"
b110100 #
#210
0"
#211
0(
0E
1"
#212
0"
#213
0/
b111 -
02
b111 0
05
b111 3
b110 6
1;
b101 9
b11 <
0A
b111 ?
b111000 &
b111000 ,
0D
b111 B
b11101111 !
b11101111 '
b11101111 *
b11101111 )
1(
1E
1"
b110101 #
#214
0"
#215
0(
0E
1"
#216
0"
#217
0/
b0 -
02
b0 0
15
b1 3
18
b11 6
0;
b111 9
b110 <
1A
b100 ?
b1101100 &
b1101100 ,
0D
b0 B
b111000 !
b111000 '
b111000 *
b111000 )
1(
1E
1"
b110110 #
#218
0"
#219
0(
0E
1"
#220
0"
#221
12
b1 0
b11 3
b110 6
1;
b101 9
1>
b11 <
b110 ?
b11111110 &
b11111110 ,
1D
b100 B
b1101100 !
b1101100 '
b1101100 *
b1101100 )
1(
1E
1"
b110111 #
#222
0"
#223
0(
0E
1"
#224
0"
#225
1/
b101 -
b11 0
05
b111 3
08
b111 6
0;
b111 9
0>
b111 <
b10000011 &
b10000011 ,
0A
b111 ?
b110 B
b11111110 !
b11111110 '
b11111110 *
b11111110 )
1(
1E
1"
b111000 #
#226
0"
#227
0(
0E
1"
#228
0"
#229
0/
b111 -
b110 0
15
b100 3
08
b0 6
0;
b0 9
0>
b0 <
1A
b1 ?
b11000110 &
b11000110 ,
1D
b11 B
b10000011 !
b10000011 '
b10000011 *
b10000011 )
1(
1E
1"
b111001 #
#230
0"
#231
0(
0E
1"
#232
0"
#233
1/
b101 -
12
b11 0
b110 3
18
b100 6
b11101111 &
b11101111 ,
1>
b1 <
b11 ?
b110 B
b11000110 !
b11000110 '
b11000110 *
b11000110 )
1(
1E
1"
b111010 #
#234
0"
#235
0(
0E
1"
#236
0"
#237
0/
b111 -
02
b111 0
05
b111 3
b110 6
1;
b101 9
b11 <
0A
b111 ?
b111000 &
b111000 ,
0D
b111 B
b11101111 !
b11101111 '
b11101111 *
b11101111 )
1(
1E
1"
b111011 #
#238
0"
#239
0(
0E
1"
#240
0"
#241
0/
b0 -
02
b0 0
15
b1 3
18
b11 6
0;
b111 9
b110 <
1A
b100 ?
b1101100 &
b1101100 ,
0D
b0 B
b111000 !
b111000 '
b111000 *
b111000 )
1(
1E
1"
b111100 #
#242
0"
#243
0(
0E
1"
#244
0"
#245
12
b1 0
b11 3
b110 6
1;
b101 9
1>
b11 <
b110 ?
b11111110 &
b11111110 ,
1D
b100 B
b1101100 !
b1101100 '
b1101100 *
b1101100 )
1(
1E
1"
b111101 #
#246
0"
#247
0(
0E
1"
#248
0"
#249
1/
b101 -
b11 0
05
b111 3
08
b111 6
0;
b111 9
0>
b111 <
b10000011 &
b10000011 ,
0A
b111 ?
b110 B
b11111110 !
b11111110 '
b11111110 *
b11111110 )
1(
1E
1"
b111110 #
#250
0"
#251
0(
0E
1"
#252
0"
#253
0/
b111 -
b110 0
15
b100 3
08
b0 6
0;
b0 9
0>
b0 <
1A
b1 ?
b11000110 &
b11000110 ,
1D
b11 B
b10000011 !
b10000011 '
b10000011 *
b10000011 )
1(
1E
1"
b111111 #
#254
0"
#255
0(
0E
1"
#256
0"
#257
1/
b101 -
12
b11 0
b110 3
18
b100 6
b11101111 &
b11101111 ,
1>
b1 <
b11 ?
b110 B
b11000110 !
b11000110 '
b11000110 *
b11000110 )
1(
1E
1"
b1000000 #
#258
0"
#259
0(
0E
1"
#260
0"
#261
0/
b111 -
02
b111 0
05
b111 3
b110 6
1;
b101 9
b11 <
0A
b111 ?
b111000 &
b111000 ,
0D
b111 B
b11101111 !
b11101111 '
b11101111 *
b11101111 )
1(
1E
1"
b1000001 #
#262
0"
#263
0(
0E
1"
#264
0"
#265
0/
b0 -
02
b0 0
15
b1 3
18
b11 6
0;
b111 9
b110 <
1A
b100 ?
b1101100 &
b1101100 ,
0D
b0 B
b111000 !
b111000 '
b111000 *
b111000 )
1(
1E
1"
b1000010 #
#266
0"
#267
0(
0E
1"
#268
0"
#269
12
b1 0
b11 3
b110 6
1;
b101 9
1>
b11 <
b110 ?
b11111110 &
b11111110 ,
1D
b100 B
b1101100 !
b1101100 '
b1101100 *
b1101100 )
1(
1E
1"
b1000011 #
#270
0"
#271
0(
0E
1"
#272
0"
#273
1/
b101 -
b11 0
05
b111 3
08
b111 6
0;
b111 9
0>
b111 <
b10000011 &
b10000011 ,
0A
b111 ?
b110 B
b11111110 !
b11111110 '
b11111110 *
b11111110 )
1(
1E
1"
b1000100 #
#274
0"
#275
0(
0E
1"
#276
0"
#277
0/
b111 -
b110 0
15
b100 3
08
b0 6
0;
b0 9
0>
b0 <
1A
b1 ?
b11000110 &
b11000110 ,
1D
b11 B
b10000011 !
b10000011 '
b10000011 *
b10000011 )
1(
1E
1"
b1000101 #
#278
0"
#279
0(
0E
1"
#280
0"
#281
1/
b101 -
12
b11 0
b110 3
18
b100 6
b11101111 &
b11101111 ,
1>
b1 <
b11 ?
b110 B
b11000110 !
b11000110 '
b11000110 *
b11000110 )
1(
1E
1"
b1000110 #
#282
0"
#283
0(
0E
1"
#284
0"
#285
0/
b111 -
02
b111 0
05
b111 3
b110 6
1;
b101 9
b11 <
0A
b111 ?
b111000 &
b111000 ,
0D
b111 B
b11101111 !
b11101111 '
b11101111 *
b11101111 )
1(
1E
1"
b1000111 #
#286
0"
#287
0(
0E
1"
#288
0"
#289
0/
b0 -
02
b0 0
15
b1 3
18
b11 6
0;
b111 9
b110 <
1A
b100 ?
b1101100 &
b1101100 ,
0D
b0 B
b111000 !
b111000 '
b111000 *
b111000 )
1(
1E
1"
b1001000 #
#290
0"
#291
0(
0E
1"
#292
0"
#293
12
b1 0
b11 3
b110 6
1;
b101 9
1>
b11 <
b110 ?
b11111110 &
b11111110 ,
1D
b100 B
b1101100 !
b1101100 '
b1101100 *
b1101100 )
1(
1E
1"
b1001001 #
#294
0"
#295
0(
0E
1"
#296
0"
#297
1/
b101 -
b11 0
05
b111 3
08
b111 6
0;
b111 9
0>
b111 <
b10000011 &
b10000011 ,
0A
b111 ?
b110 B
b11111110 !
b11111110 '
b11111110 *
b11111110 )
1(
1E
1"
b1001010 #
#298
0"
#299
0(
0E
1"
#300
0"
#301
0/
b111 -
b110 0
15
b100 3
08
b0 6
0;
b0 9
0>
b0 <
1A
b1 ?
b11000110 &
b11000110 ,
1D
b11 B
b10000011 !
b10000011 '
b10000011 *
b10000011 )
1(
1E
1"
b1001011 #
#302
0"
#303
0(
0E
1"
#304
0"
#305
1/
b101 -
12
b11 0
b110 3
18
b100 6
b11101111 &
b11101111 ,
1>
b1 <
b11 ?
b110 B
b11000110 !
b11000110 '
b11000110 *
b11000110 )
1(
1E
1"
b1001100 #
#306
0"
#307
0(
0E
1"
#308
0"
#309
0/
b111 -
02
b111 0
05
b111 3
b110 6
1;
b101 9
b11 <
0A
b111 ?
b111000 &
b111000 ,
0D
b111 B
b11101111 !
b11101111 '
b11101111 *
b11101111 )
1(
1E
1"
b1001101 #
#310
0"
#311
0(
0E
1"
#312
0"
#313
0/
b0 -
02
b0 0
15
b1 3
18
b11 6
0;
b111 9
b110 <
1A
b100 ?
b1101100 &
b1101100 ,
0D
b0 B
b111000 !
b111000 '
b111000 *
b111000 )
1(
1E
1"
b1001110 #
#314
0"
#315
0(
0E
1"
#316
0"
#317
12
b1 0
b11 3
b110 6
1;
b101 9
1>
b11 <
b110 ?
b11111110 &
b11111110 ,
1D
b100 B
b1101100 !
b1101100 '
b1101100 *
b1101100 )
1(
1E
1"
b1001111 #
#318
0"
#319
0(
0E
1"
#320
0"
#321
1/
b101 -
b11 0
05
b111 3
08
b111 6
0;
b111 9
0>
b111 <
b10000011 &
b10000011 ,
0A
b111 ?
b110 B
b11111110 !
b11111110 '
b11111110 *
b11111110 )
1(
1E
1"
b1010000 #
#322
0"
#323
0(
0E
1"
#324
0"
#325
0/
b111 -
b110 0
15
b100 3
08
b0 6
0;
b0 9
0>
b0 <
1A
b1 ?
b11000110 &
b11000110 ,
1D
b11 B
b10000011 !
b10000011 '
b10000011 *
b10000011 )
1(
1E
1"
b1010001 #
#326
0"
