block.v
module block(in, rule, out);
    input wire[2:0] in;
    input wire[7:0] rule;

    output wire out;

    assign out = rule[in];
endmodule

Automaton-Verilog-Nbits/automaton.v
module automaton #(parameter WIDTH = 8) 
  ( input wire clk,           //-- IN: Reloj de la FPGA
    output wire [WIDTH-1:0] data    //-- OUT: Salida del Cellular Automaton --> a los leds
  );

  //-- Bits para el prescaler
  parameter N = 23;
  parameter SEED = 8'b00000001; // 1a linea (semilla) del Cellular Automaton
  parameter RULE = 129;
  
  wire [7:0] rule = RULE;

  //-- Reloj principal (prescalado)
  wire clk_base;

  //-- Instanciar el prescaler
  prescaler #(.N(N)) PRES ( .clk_in(clk), .clk_out(clk_base) );

  //-- Instanciar el Inicializador
  wire sel;
  init INIT ( clk_base, sel );

  // ver Diseño del T13  --> inicializador --> selector (mux2-1)

  //-- Cable salida del cellAutomaton (CA) al registro R
  wire [WIDTH-1:0] rin;

  // mux2-1 (saca SEED si sel=0, sino la salida del registro (detras del Cellular Automaton))
  assign data = (sel == 0) ? SEED : rout;

  cellAutomaton #(.WIDTH(WIDTH)) CA ( .in(data), .rule(rule), .out(rin));

  //-- Registro R de WIDTH bits
  reg [WIDTH-1:0] rout;
  always @(posedge(clk_base))
    rout <= rin; // Pasamos la salida del Cellular Automaton a la salida del registro en cada positive edge

endmodule

module cellAutomaton #(parameter WIDTH = 8) 
  ( input wire [WIDTH-1:0] in,
    input wire [7:0] rule,
    output wire [WIDTH-1:0] out
  );

  //-- Apply the Cellular Automaton rule (compute "next line")
  // block B0( { in[7], in[0], in[1] }, rule, out[0] );
  // block B1( { in[0], in[1], in[2] }, rule, out[1] );
  // block B2( { in[1], in[2], in[3] }, rule, out[2] );
  // block B3( { in[2], in[3], in[4] }, rule, out[3] );
  // block B4( { in[3], in[4], in[5] }, rule, out[4] );
  // block B5( { in[4], in[5], in[6] }, rule, out[5] );
  // block B6( { in[5], in[6], in[7] }, rule, out[6] );
  // block B7( { in[6], in[7], in[0] }, rule, out[7] );

  genvar i;
  generate
    for (i=0; i<WIDTH; i=i+1)
    begin : automaton_cell
      block Bi( { in[ (i==0) ? WIDTH-1 : (i-1) ], in[i], in[ ( i == (WIDTH-1) ) ? 0 : i+1 ] }, rule, out[i] );
      // case (i)
      //   0:  
      //     block B0( { in[WIDTH-1], in[0], in[1] }, rule, out[0] );
      //   WIDTH-1:
      //     block BW( { in[WIDTH-2], in[WIDTH-1], in[0] }, rule, out[WIDTH-1] );
      //   default: 
      //     block Bi( { in[i-1], in[i], in[i+1] }, rule, out[i] );
      // endcase
    end 
  endgenerate

endmodule

Automaton-Verilog-Nbits/init.v
//-- init.v  (version optimizada)
module init(input wire clk, output ini);
    //-- Registro de 1 bit inicializa a 0 (solo para simulacion)
    //-- Al sintetizarlo siempre estará a cero con independencia 
    //-- del valor al que lo pongamos
    reg ini = 0;

    //-- En flanco de subida sacamos un "1" por la salida
    always @(posedge(clk))
        ini <= 1;

endmodule

Automaton-VGA-80bit/prescaler.v
//-------------------------------------------------------------
//-- Prescaler de N bits
//-- (C) BQ. August 2015. Written by Juan Gonzalez (obijuan)
//-------------------------------------------------------------
//-- Prescaler generico, para ralentizar las señales de reloj
//-------------------------------------------------------------

//-- Entrada: señal de reloj de entrada
//-- Salida: Señal de reloj de salida, con menor frecuencia

`default_nettype none

module prescaler(input clk_in, output clk_out);
  wire clk_in;
  wire clk_out;

  //-- Numero de bits del prescaler (por defecto)
  parameter N = 22;

  //-- Registro para implementar contador de N bits
  reg [N-1:0] count = 0;

  //-- El bit más significativo se saca por la salida
  assign clk_out = count[N-1];

  //-- Contador: se incrementa en flanco de subida
  always @(posedge(clk_in)) begin
    count <= count + 1;
  end

endmodule

Automaton-Verilog-Nbits/automaton_tb.v
module automaton_tb();

	parameter WIDTH = 80;

    reg[7:0] count = 0;

	//-- Registro para generar la señal de reloj
	reg clk = 0;

	//-- Datos de salida del componente
	wire [WIDTH-1:0] data;

	//-- Instanciar el componente (N=1 aqui, segundos)
	automaton #(.WIDTH(WIDTH)) myCA ( .clk(clk), .data(data) );
	defparam myCA.N=1;
	defparam myCA.RULE=126; // http://mathworld.wolfram.com/Rule126.html
	defparam myCA.SEED = 2**(WIDTH/2);

	//-- Generador de reloj. Periodo 2 unidades
	always #1 clk = ~clk;

	integer file;

	//-- Proceso al inicio
	initial begin

		//-- Fichero donde almacenar los resultados
		$dumpfile("automaton_tb.vcd");
		$dumpvars(0, automaton_tb);

		#1 $display("data: %b (%d)", data, count);

		file = $fopen("data.out", "wb");
		$fwrite(file, "%b\n", data);

        for (count=1; count<=59; count=count+1)
        begin
            #4
            $display("data: %b (%d)", data, count);
			$fwrite(file, "%b\n", data);
        end

		$fclose(file);
		# 1 $display("FIN de la simulacion");
		$finish;

	end

endmodule

Automaton-Verilog-Nbits/automaton_tb.vcd
$date
	Mon Apr  2 21:21:55 2018
$end
$version
	Icarus Verilog
$end
$timescale
	1s
$end
$scope module automaton_tb $end
$var wire 80 ! data [79:0] $end
$var reg 1 " clk $end
$var reg 8 # count [7:0] $end
$var integer 32 $ file [31:0] $end
$scope module myCA $end
$var wire 1 % clk $end
$var wire 1 & clk_base $end
$var wire 80 ' data [79:0] $end
$var wire 80 ( rin [79:0] $end
$var wire 8 ) rule [7:0] $end
$var wire 1 * sel $end
$var reg 80 + rout [79:0] $end
$scope module PRES $end
$var wire 1 % clk_in $end
$var wire 1 & clk_out $end
$var reg 1 , count $end
$upscope $end
$scope module INIT $end
$var wire 1 & clk $end
$var reg 1 - ini $end
$upscope $end
$scope module CA $end
$var wire 80 . in [79:0] $end
$var wire 80 / out [79:0] $end
$var wire 8 0 rule [7:0] $end
$scope begin automaton_cell[0] $end
$scope module Bi $end
$var wire 3 1 in [2:0] $end
$var wire 1 2 out $end
$var wire 8 3 rule [7:0] $end
$upscope $end
$upscope $end
$scope begin automaton_cell[1] $end
$scope module Bi $end
$var wire 3 4 in [2:0] $end
$var wire 1 5 out $end
$var wire 8 6 rule [7:0] $end
$upscope $end
$upscope $end
$scope begin automaton_cell[2] $end
$scope module Bi $end
$var wire 3 7 in [2:0] $end
$var wire 1 8 out $end
$var wire 8 9 rule [7:0] $end
$upscope $end
$upscope $end
$scope begin automaton_cell[3] $end
$scope module Bi $end
$var wire 3 : in [2:0] $end
$var wire 1 ; out $end
$var wire 8 < rule [7:0] $end
$upscope $end
$upscope $end
$scope begin automaton_cell[4] $end
$scope module Bi $end
$var wire 3 = in [2:0] $end
$var wire 1 > out $end
$var wire 8 ? rule [7:0] $end
$upscope $end
$upscope $end
$scope begin automaton_cell[5] $end
$scope module Bi $end
$var wire 3 @ in [2:0] $end
$var wire 1 A out $end
$var wire 8 B rule [7:0] $end
$upscope $end
$upscope $end
$scope begin automaton_cell[6] $end
$scope module Bi $end
$var wire 3 C in [2:0] $end
$var wire 1 D out $end
$var wire 8 E rule [7:0] $end
$upscope $end
$upscope $end
$scope begin automaton_cell[7] $end
$scope module Bi $end
$var wire 3 F in [2:0] $end
$var wire 1 G out $end
$var wire 8 H rule [7:0] $end
$upscope $end
$upscope $end
$scope begin automaton_cell[8] $end
$scope module Bi $end
$var wire 3 I in [2:0] $end
$var wire 1 J out $end
$var wire 8 K rule [7:0] $end
$upscope $end
$upscope $end
$scope begin automaton_cell[9] $end
$scope module Bi $end
$var wire 3 L in [2:0] $end
$var wire 1 M out $end
$var wire 8 N rule [7:0] $end
$upscope $end
$upscope $end
$scope begin automaton_cell[10] $end
$scope module Bi $end
$var wire 3 O in [2:0] $end
$var wire 1 P out $end
$var wire 8 Q rule [7:0] $end
$upscope $end
$upscope $end
$scope begin automaton_cell[11] $end
$scope module Bi $end
$var wire 3 R in [2:0] $end
$var wire 1 S out $end
$var wire 8 T rule [7:0] $end
$upscope $end
$upscope $end
$scope begin automaton_cell[12] $end
$scope module Bi $end
$var wire 3 U in [2:0] $end
$var wire 1 V out $end
$var wire 8 W rule [7:0] $end
$upscope $end
$upscope $end
$scope begin automaton_cell[13] $end
$scope module Bi $end
$var wire 3 X in [2:0] $end
$var wire 1 Y out $end
$var wire 8 Z rule [7:0] $end
$upscope $end
$upscope $end
$scope begin automaton_cell[14] $end
$scope module Bi $end
$var wire 3 [ in [2:0] $end
$var wire 1 \ out $end
$var wire 8 ] rule [7:0] $end
$upscope $end
$upscope $end
$scope begin automaton_cell[15] $end
$scope module Bi $end
$var wire 3 ^ in [2:0] $end
$var wire 1 _ out $end
$var wire 8 ` rule [7:0] $end
$upscope $end
$upscope $end
$scope begin automaton_cell[16] $end
$scope module Bi $end
$var wire 3 a in [2:0] $end
$var wire 1 b out $end
$var wire 8 c rule [7:0] $end
$upscope $end
$upscope $end
$scope begin automaton_cell[17] $end
$scope module Bi $end
$var wire 3 d in [2:0] $end
$var wire 1 e out $end
$var wire 8 f rule [7:0] $end
$upscope $end
$upscope $end
$scope begin automaton_cell[18] $end
$scope module Bi $end
$var wire 3 g in [2:0] $end
$var wire 1 h out $end
$var wire 8 i rule [7:0] $end
$upscope $end
$upscope $end
$scope begin automaton_cell[19] $end
$scope module Bi $end
$var wire 3 j in [2:0] $end
$var wire 1 k out $end
$var wire 8 l rule [7:0] $end
$upscope $end
$upscope $end
$scope begin automaton_cell[20] $end
$scope module Bi $end
$var wire 3 m in [2:0] $end
$var wire 1 n out $end
$var wire 8 o rule [7:0] $end
$upscope $end
$upscope $end
$scope begin automaton_cell[21] $end
$scope module Bi $end
$var wire 3 p in [2:0] $end
$var wire 1 q out $end
$var wire 8 r rule [7:0] $end
$upscope $end
$upscope $end
$scope begin automaton_cell[22] $end
$scope module Bi $end
$var wire 3 s in [2:0] $end
$var wire 1 t out $end
$var wire 8 u rule [7:0] $end
$upscope $end
$upscope $end
$scope begin automaton_cell[23] $end
$scope module Bi $end
$var wire 3 v in [2:0] $end
$var wire 1 w out $end
$var wire 8 x rule [7:0] $end
$upscope $end
$upscope $end
$scope begin automaton_cell[24] $end
$scope module Bi $end
$var wire 3 y in [2:0] $end
$var wire 1 z out $end
$var wire 8 { rule [7:0] $end
$upscope $end
$upscope $end
$scope begin automaton_cell[25] $end
$scope module Bi $end
$var wire 3 | in [2:0] $end
$var wire 1 } out $end
$var wire 8 ~ rule [7:0] $end
$upscope $end
$upscope $end
$scope begin automaton_cell[26] $end
$scope module Bi $end
$var wire 3 !" in [2:0] $end
$var wire 1 "" out $end
$var wire 8 #" rule [7:0] $end
$upscope $end
$upscope $end
$scope begin automaton_cell[27] $end
$scope module Bi $end
$var wire 3 $" in [2:0] $end
$var wire 1 %" out $end
$var wire 8 &" rule [7:0] $end
$upscope $end
$upscope $end
$scope begin automaton_cell[28] $end
$scope module Bi $end
$var wire 3 '" in [2:0] $end
$var wire 1 (" out $end
$var wire 8 )" rule [7:0] $end
$upscope $end
$upscope $end
$scope begin automaton_cell[29] $end
$scope module Bi $end
$var wire 3 *" in [2:0] $end
$var wire 1 +" out $end
$var wire 8 ," rule [7:0] $end
$upscope $end
$upscope $end
$scope begin automaton_cell[30] $end
$scope module Bi $end
$var wire 3 -" in [2:0] $end
$var wire 1 ." out $end
$var wire 8 /" rule [7:0] $end
$upscope $end
$upscope $end
$scope begin automaton_cell[31] $end
$scope module Bi $end
$var wire 3 0" in [2:0] $end
$var wire 1 1" out $end
$var wire 8 2" rule [7:0] $end
$upscope $end
$upscope $end
$scope begin automaton_cell[32] $end
$scope module Bi $end
$var wire 3 3" in [2:0] $end
$var wire 1 4" out $end
$var wire 8 5" rule [7:0] $end
$upscope $end
$upscope $end
$scope begin automaton_cell[33] $end
$scope module Bi $end
$var wire 3 6" in [2:0] $end
$var wire 1 7" out $end
$var wire 8 8" rule [7:0] $end
$upscope $end
$upscope $end
$scope begin automaton_cell[34] $end
$scope module Bi $end
$var wire 3 9" in [2:0] $end
$var wire 1 :" out $end
$var wire 8 ;" rule [7:0] $end
$upscope $end
$upscope $end
$scope begin automaton_cell[35] $end
$scope module Bi $end
$var wire 3 <" in [2:0] $end
$var wire 1 =" out $end
$var wire 8 >" rule [7:0] $end
$upscope $end
$upscope $end
$scope begin automaton_cell[36] $end
$scope module Bi $end
$var wire 3 ?" in [2:0] $end
$var wire 1 @" out $end
$var wire 8 A" rule [7:0] $end
$upscope $end
$upscope $end
$scope begin automaton_cell[37] $end
$scope module Bi $end
$var wire 3 B" in [2:0] $end
$var wire 1 C" out $end
$var wire 8 D" rule [7:0] $end
$upscope $end
$upscope $end
$scope begin automaton_cell[38] $end
$scope module Bi $end
$var wire 3 E" in [2:0] $end
$var wire 1 F" out $end
$var wire 8 G" rule [7:0] $end
$upscope $end
$upscope $end
$scope begin automaton_cell[39] $end
$scope module Bi $end
$var wire 3 H" in [2:0] $end
$var wire 1 I" out $end
$var wire 8 J" rule [7:0] $end
$upscope $end
$upscope $end
$scope begin automaton_cell[40] $end
$scope module Bi $end
$var wire 3 K" in [2:0] $end
$var wire 1 L" out $end
$var wire 8 M" rule [7:0] $end
$upscope $end
$upscope $end
$scope begin automaton_cell[41] $end
$scope module Bi $end
$var wire 3 N" in [2:0] $end
$var wire 1 O" out $end
$var wire 8 P" rule [7:0] $end
$upscope $end
$upscope $end
$scope begin automaton_cell[42] $end
$scope module Bi $end
$var wire 3 Q" in [2:0] $end
$var wire 1 R" out $end
$var wire 8 S" rule [7:0] $end
$upscope $end
$upscope $end
$scope begin automaton_cell[43] $end
$scope module Bi $end
$var wire 3 T" in [2:0] $end
$var wire 1 U" out $end
$var wire 8 V" rule [7:0] $end
$upscope $end
$upscope $end
$scope begin automaton_cell[44] $end
$scope module Bi $end
$var wire 3 W" in [2:0] $end
$var wire 1 X" out $end
$var wire 8 Y" rule [7:0] $end
$upscope $end
$upscope $end
$scope begin automaton_cell[45] $end
$scope module Bi $end
$var wire 3 Z" in [2:0] $end
$var wire 1 [" out $end
$var wire 8 \" rule [7:0] $end
$upscope $end
$upscope $end
$scope begin automaton_cell[46] $end
$scope module Bi $end
$var wire 3 ]" in [2:0] $end
$var wire 1 ^" out $end
$var wire 8 _" rule [7:0] $end
$upscope $end
$upscope $end
$scope begin automaton_cell[47] $end
$scope module Bi $end
$var wire 3 `" in [2:0] $end
$var wire 1 a" out $end
$var wire 8 b" rule [7:0] $end
$upscope $end
$upscope $end
$scope begin automaton_cell[48] $end
$scope module Bi $end
$var wire 3 c" in [2:0] $end
$var wire 1 d" out $end
$var wire 8 e" rule [7:0] $end
$upscope $end
$upscope $end
$scope begin automaton_cell[49] $end
$scope module Bi $end
$var wire 3 f" in [2:0] $end
$var wire 1 g" out $end
$var wire 8 h" rule [7:0] $end
$upscope $end
$upscope $end
$scope begin automaton_cell[50] $end
$scope module Bi $end
$var wire 3 i" in [2:0] $end
$var wire 1 j" out $end
$var wire 8 k" rule [7:0] $end
$upscope $end
$upscope $end
$scope begin automaton_cell[51] $end
$scope module Bi $end
$var wire 3 l" in [2:0] $end
$var wire 1 m" out $end
$var wire 8 n" rule [7:0] $end
$upscope $end
$upscope $end
$scope begin automaton_cell[52] $end
$scope module Bi $end
$var wire 3 o" in [2:0] $end
$var wire 1 p" out $end
$var wire 8 q" rule [7:0] $end
$upscope $end
$upscope $end
$scope begin automaton_cell[53] $end
$scope module Bi $end
$var wire 3 r" in [2:0] $end
$var wire 1 s" out $end
$var wire 8 t" rule [7:0] $end
$upscope $end
$upscope $end
$scope begin automaton_cell[54] $end
$scope module Bi $end
$var wire 3 u" in [2:0] $end
$var wire 1 v" out $end
$var wire 8 w" rule [7:0] $end
$upscope $end
$upscope $end
$scope begin automaton_cell[55] $end
$scope module Bi $end
$var wire 3 x" in [2:0] $end
$var wire 1 y" out $end
$var wire 8 z" rule [7:0] $end
$upscope $end
$upscope $end
$scope begin automaton_cell[56] $end
$scope module Bi $end
$var wire 3 {" in [2:0] $end
$var wire 1 |" out $end
$var wire 8 }" rule [7:0] $end
$upscope $end
$upscope $end
$scope begin automaton_cell[57] $end
$scope module Bi $end
$var wire 3 ~" in [2:0] $end
$var wire 1 !# out $end
$var wire 8 "# rule [7:0] $end
$upscope $end
$upscope $end
$scope begin automaton_cell[58] $end
$scope module Bi $end
$var wire 3 ## in [2:0] $end
$var wire 1 $# out $end
$var wire 8 %# rule [7:0] $end
$upscope $end
$upscope $end
$scope begin automaton_cell[59] $end
$scope module Bi $end
$var wire 3 &# in [2:0] $end
$var wire 1 '# out $end
$var wire 8 (# rule [7:0] $end
$upscope $end
$upscope $end
$scope begin automaton_cell[60] $end
$scope module Bi $end
$var wire 3 )# in [2:0] $end
$var wire 1 *# out $end
$var wire 8 +# rule [7:0] $end
$upscope $end
$upscope $end
$scope begin automaton_cell[61] $end
$scope module Bi $end
$var wire 3 ,# in [2:0] $end
$var wire 1 -# out $end
$var wire 8 .# rule [7:0] $end
$upscope $end
$upscope $end
$scope begin automaton_cell[62] $end
$scope module Bi $end
$var wire 3 /# in [2:0] $end
$var wire 1 0# out $end
$var wire 8 1# rule [7:0] $end
$upscope $end
$upscope $end
$scope begin automaton_cell[63] $end
$scope module Bi $end
$var wire 3 2# in [2:0] $end
$var wire 1 3# out $end
$var wire 8 4# rule [7:0] $end
$upscope $end
$upscope $end
$scope begin automaton_cell[64] $end
$scope module Bi $end
$var wire 3 5# in [2:0] $end
$var wire 1 6# out $end
$var wire 8 7# rule [7:0] $end
$upscope $end
$upscope $end
$scope begin automaton_cell[65] $end
$scope module Bi $end
$var wire 3 8# in [2:0] $end
$var wire 1 9# out $end
$var wire 8 :# rule [7:0] $end
$upscope $end
$upscope $end
$scope begin automaton_cell[66] $end
$scope module Bi $end
$var wire 3 ;# in [2:0] $end
$var wire 1 <# out $end
$var wire 8 =# rule [7:0] $end
$upscope $end
$upscope $end
$scope begin automaton_cell[67] $end
$scope module Bi $end
$var wire 3 ># in [2:0] $end
$var wire 1 ?# out $end
$var wire 8 @# rule [7:0] $end
$upscope $end
$upscope $end
$scope begin automaton_cell[68] $end
$scope module Bi $end
$var wire 3 A# in [2:0] $end
$var wire 1 B# out $end
$var wire 8 C# rule [7:0] $end
$upscope $end
$upscope $end
$scope begin automaton_cell[69] $end
$scope module Bi $end
$var wire 3 D# in [2:0] $end
$var wire 1 E# out $end
$var wire 8 F# rule [7:0] $end
$upscope $end
$upscope $end
$scope begin automaton_cell[70] $end
$scope module Bi $end
$var wire 3 G# in [2:0] $end
$var wire 1 H# out $end
$var wire 8 I# rule [7:0] $end
$upscope $end
$upscope $end
$scope begin automaton_cell[71] $end
$scope module Bi $end
$var wire 3 J# in [2:0] $end
$var wire 1 K# out $end
$var wire 8 L# rule [7:0] $end
$upscope $end
$upscope $end
$scope begin automaton_cell[72] $end
$scope module Bi $end
$var wire 3 M# in [2:0] $end
$var wire 1 N# out $end
$var wire 8 O# rule [7:0] $end
$upscope $end
$upscope $end
$scope begin automaton_cell[73] $end
$scope module Bi $end
$var wire 3 P# in [2:0] $end
$var wire 1 Q# out $end
$var wire 8 R# rule [7:0] $end
$upscope $end
$upscope $end
$scope begin automaton_cell[74] $end
$scope module Bi $end
$var wire 3 S# in [2:0] $end
$var wire 1 T# out $end
$var wire 8 U# rule [7:0] $end
$upscope $end
$upscope $end
$scope begin automaton_cell[75] $end
$scope module Bi $end
$var wire 3 V# in [2:0] $end
$var wire 1 W# out $end
$var wire 8 X# rule [7:0] $end
$upscope $end
$upscope $end
$scope begin automaton_cell[76] $end
$scope module Bi $end
$var wire 3 Y# in [2:0] $end
$var wire 1 Z# out $end
$var wire 8 [# rule [7:0] $end
$upscope $end
$upscope $end
$scope begin automaton_cell[77] $end
$scope module Bi $end
$var wire 3 \# in [2:0] $end
$var wire 1 ]# out $end
$var wire 8 ^# rule [7:0] $end
$upscope $end
$upscope $end
$scope begin automaton_cell[78] $end
$scope module Bi $end
$var wire 3 _# in [2:0] $end
$var wire 1 `# out $end
$var wire 8 a# rule [7:0] $end
$upscope $end
$upscope $end
$scope begin automaton_cell[79] $end
$scope module Bi $end
$var wire 3 b# in [2:0] $end
$var wire 1 c# out $end
$var wire 8 d# rule [7:0] $end
$upscope $end
$upscope $end
$upscope $end
$upscope $end
$upscope $end
$enddefinitions $end
#0
$dumpvars
b1111110 d#
0c#
b0 b#
b1111110 a#
0`#
b0 _#
b1111110 ^#
0]#
b0 \#
b1111110 [#
0Z#
b0 Y#
b1111110 X#
0W#
b0 V#
b1111110 U#
0T#
b0 S#
b1111110 R#
0Q#
b0 P#
b1111110 O#
0N#
b0 M#
b1111110 L#
0K#
b0 J#
b1111110 I#
0H#
b0 G#
b1111110 F#
0E#
b0 D#
b1111110 C#
0B#
b0 A#
b1111110 @#
0?#
b0 >#
b1111110 =#
0<#
b0 ;#
b1111110 :#
09#
b0 8#
b1111110 7#
06#
b0 5#
b1111110 4#
03#
b0 2#
b1111110 1#
00#
b0 /#
b1111110 .#
0-#
b0 ,#
b1111110 +#
0*#
b0 )#
b1111110 (#
0'#
b0 &#
b1111110 %#
0$#
b0 ##
b1111110 "#
0!#
b0 ~"
b1111110 }"
0|"
b0 {"
b1111110 z"
0y"
b0 x"
b1111110 w"
0v"
b0 u"
b1111110 t"
0s"
b0 r"
b1111110 q"
0p"
b0 o"
b1111110 n"
0m"
b0 l"
b1111110 k"
0j"
b0 i"
b1111110 h"
0g"
b0 f"
b1111110 e"
0d"
b0 c"
b1111110 b"
0a"
b0 `"
b1111110 _"
0^"
b0 ]"
b1111110 \"
0["
b0 Z"
b1111110 Y"
0X"
b0 W"
b1111110 V"
0U"
b0 T"
b1111110 S"
0R"
b0 Q"
b1111110 P"
1O"
b100 N"
b1111110 M"
1L"
b10 K"
b1111110 J"
1I"
b1 H"
b1111110 G"
0F"
b0 E"
b1111110 D"
0C"
b0 B"
b1111110 A"
0@"
b0 ?"
b1111110 >"
0="
b0 <"
b1111110 ;"
0:"
b0 9"
b1111110 8"
07"
b0 6"
b1111110 5"
04"
b0 3"
b1111110 2"
01"
b0 0"
b1111110 /"
0."
b0 -"
b1111110 ,"
0+"
b0 *"
b1111110 )"
0("
b0 '"
b1111110 &"
0%"
b0 $"
b1111110 #"
0""
b0 !"
b1111110 ~
0}
b0 |
b1111110 {
0z
b0 y
b1111110 x
0w
b0 v
b1111110 u
0t
b0 s
b1111110 r
0q
b0 p
b1111110 o
0n
b0 m
b1111110 l
0k
b0 j
b1111110 i
0h
b0 g
b1111110 f
0e
b0 d
b1111110 c
0b
b0 a
b1111110 `
0_
b0 ^
b1111110 ]
0\
b0 [
b1111110 Z
0Y
b0 X
b1111110 W
0V
b0 U
b1111110 T
0S
b0 R
b1111110 Q
0P
b0 O
b1111110 N
0M
b0 L
b1111110 K
0J
b0 I
b1111110 H
0G
b0 F
b1111110 E
0D
b0 C
b1111110 B
0A
b0 @
b1111110 ?
0>
b0 =
b1111110 <
0;
b0 :
b1111110 9
08
b0 7
b1111110 6
05
b0 4
b1111110 3
02
b0 1
b1111110 0
b111000000000000000000000000000000000000000 /
b10000000000000000000000000000000000000000 .
0-
0,
bx +
0*
b1111110 )
b111000000000000000000000000000000000000000 (
b10000000000000000000000000000000000000000 '
0&
0%
bx $
b0 #
0"
b10000000000000000000000000000000000000000 !
$end
#1
b1 E"
1F"
b11 H"
0L"
b111 K"
b110 N"
b100 Q"
1R"
b1101100000000000000000000000000000000000000 (
b1101100000000000000000000000000000000000000 /
b111000000000000000000000000000000000000000 !
b111000000000000000000000000000000000000000 '
b111000000000000000000000000000000000000000 .
1-
1*
b111000000000000000000000000000000000000000 +
1,
1&
b1 #
b10000000000000000000000000000011 $
1"
1%
#2
0"
0%
#3
0,
0&
1"
1%
#4
0"
0%
#5
b1 B"
1C"
b11 E"
b110 H"
b101 K"
1L"
b11 N"
1O"
b110 Q"
b100 T"
1U"
b11111110000000000000000000000000000000000000 (
b11111110000000000000000000000000000000000000 /
b1101100000000000000000000000000000000000000 !
b1101100000000000000000000000000000000000000 '
b1101100000000000000000000000000000000000000 .
b1101100000000000000000000000000000000000000 +
1,
1&
1"
1%
b10 #
#6
0"
0%
#7
0,
0&
1"
1%
#8
0"
0%
#9
b1 ?"
1@"
b11 B"
b111 E"
0F"
b111 H"
0I"
b111 K"
0L"
b111 N"
0O"
b111 Q"
0R"
b110 T"
b100 W"
1X"
b110000011000000000000000000000000000000000000 (
b110000011000000000000000000000000000000000000 /
b11111110000000000000000000000000000000000000 !
b11111110000000000000000000000000000000000000 '
b11111110000000000000000000000000000000000000 .
b11111110000000000000000000000000000000000000 +
1,
1&
1"
1%
b11 #
#10
0"
0%
#11
0,
0&
1"
1%
#12
0"
0%
#13
b1 <"
1="
b11 ?"
b110 B"
b100 E"
1F"
b0 H"
0I"
b0 K"
0L"
b0 N"
0O"
b1 Q"
1R"
b11 T"
1U"
b110 W"
b100 Z"
1["
b1111000111100000000000000000000000000000000000 (
b1111000111100000000000000000000000000000000000 /
b110000011000000000000000000000000000000000000 !
b110000011000000000000000000000000000000000000 '
b110000011000000000000000000000000000000000000 .
b110000011000000000000000000000000000000000000 +
1,
1&
1"
1%
b100 #
#14
0"
0%
#15
0,
0&
1"
1%
#16
0"
0%
#17
b1 9"
1:"
b11 <"
b111 ?"
0@"
b111 B"
0C"
b110 E"
b100 H"
1I"
b1 N"
1O"
b11 Q"
b111 T"
0U"
b111 W"
0X"
b110 Z"
b100 ]"
1^"
b11001101100110000000000000000000000000000000000 (
b11001101100110000000000000000000000000000000000 /
b1111000111100000000000000000000000000000000000 !
b1111000111100000000000000000000000000000000000 '
b1111000111100000000000000000000000000000000000 .
b1111000111100000000000000000000000000000000000 +
1,
1&
1"
1%
b101 #
#18
0"
0%
#19
0,
0&
1"
1%
#20
0"
0%
#21
b1 6"
17"
b11 9"
b110 <"
b100 ?"
1@"
b1 B"
1C"
b11 E"
1F"
b110 H"
b101 K"
1L"
b11 N"
b110 Q"
b100 T"
1U"
b1 W"
1X"
b11 Z"
1["
b110 ]"
b100 `"
1a"
b111111111111111000000000000000000000000000000000 (
b111111111111111000000000000000000000000000000000 /
b11001101100110000000000000000000000000000000000 !
b11001101100110000000000000000000000000000000000 '
b11001101100110000000000000000000000000000000000 .
b11001101100110000000000000000000000000000000000 +
1,
1&
1"
1%
b110 #
#22
0"
0%
#23
0,
0&
1"
1%
#24
0"
0%
#25
b1 3"
14"
b11 6"
b111 9"
0:"
b111 <"
0="
0@"
b111 ?"
0C"
b111 B"
b111 E"
0F"
b111 H"
0I"
b111 K"
0L"
b111 N"
0O"
b111 Q"
0R"
0U"
b111 T"
0X"
b111 W"
b111 Z"
0["
b111 ]"
0^"
b110 `"
b100 c"
1d"
b1100000000000001100000000000000000000000000000000 (
b1100000000000001100000000000000000000000000000000 /
b111111111111111000000000000000000000000000000000 !
b111111111111111000000000000000000000000000000000 '
b111111111111111000000000000000000000000000000000 .
b111111111111111000000000000000000000000000000000 +
1,
1&
1"
1%
b111 #
#26
0"
0%
#27
0,
0&
1"
1%
#28
0"
0%
#29
b1 0"
11"
b11 3"
b110 6"
b100 9"
1:"
b0 <"
0="
b0 ?"
0@"
b0 B"
0C"
b0 E"
0F"
b0 H"
0I"
b0 K"
0L"
b0 N"
0O"
b0 Q"
0R"
b0 T"
0U"
b0 W"
0X"
b0 Z"
0["
b1 ]"
1^"
b11 `"
1a"
b110 c"
b100 f"
1g"
b11110000000000011110000000000000000000000000000000 (
b11110000000000011110000000000000000000000000000000 /
b1100000000000001100000000000000000000000000000000 !
b1100000000000001100000000000000000000000000000000 '
b1100000000000001100000000000000000000000000000000 .
b1100000000000001100000000000000000000000000000000 +
1,
1&
1"
1%
b1000 #
#30
0"
0%
#31
0,
0&
1"
1%
#32
0"
0%
#33
b1 -"
1."
b11 0"
b111 3"
04"
b111 6"
07"
b110 9"
b100 <"
1="
b1 Z"
1["
b11 ]"
b111 `"
0a"
b111 c"
0d"
b110 f"
b100 i"
1j"
b110011000000000110011000000000000000000000000000000 (
b110011000000000110011000000000000000000000000000000 /
b11110000000000011110000000000000000000000000000000 !
b11110000000000011110000000000000000000000000000000 '
b11110000000000011110000000000000000000000000000000 .
b11110000000000011110000000000000000000000000000000 +
1,
1&
1"
1%
b1001 #
#34
0"
0%
#35
0,
0&
1"
1%
#36
0"
0%
#37
b1 *"
1+"
b11 -"
b110 0"
b100 3"
14"
b1 6"
17"
b11 9"
1:"
b110 <"
b100 ?"
1@"
b1 W"
1X"
b11 Z"
b110 ]"
b100 `"
1a"
b1 c"
1d"
b11 f"
1g"
b110 i"
b100 l"
1m"
b1111111100000001111111100000000000000000000000000000 (
b1111111100000001111111100000000000000000000000000000 /
b110011000000000110011000000000000000000000000000000 !
b110011000000000110011000000000000000000000000000000 '
b110011000000000110011000000000000000000000000000000 .
b110011000000000110011000000000000000000000000000000 +
1,
1&
1"
1%
b1010 #
#38
0"
0%
#39
0,
0&
1"
1%
#40
0"
0%
#41
b1 '"
1("
b11 *"
b111 -"
0."
b111 0"
01"
04"
b111 3"
07"
b111 6"
b111 9"
0:"
b111 <"
0="
b110 ?"
b100 B"
1C"
b1 T"
1U"
b11 W"
b111 Z"
0["
b111 ]"
0^"
0a"
b111 `"
0d"
b111 c"
b111 f"
0g"
b111 i"
0j"
b110 l"
b100 o"
1p"
b11000000110000011000000110000000000000000000000000000 (
b11000000110000011000000110000000000000000000000000000 /
b1111111100000001111111100000000000000000000000000000 !
b1111111100000001111111100000000000000000000000000000 '
b1111111100000001111111100000000000000000000000000000 .
b1111111100000001111111100000000000000000000000000000 +
1,
1&
1"
1%
b1011 #
#42
0"
0%
#43
0,
0&
1"
1%
#44
0"
0%
